Workbook

Sheet Lisez-moi
A1: ScolaPay — Modèle financier (FCFA)
A3: Comment utiliser ce fichier
A4: 1. Modifiez uniquement les cellules en BLEU (onglets « Hypothèses », « Trésorerie An 1 » ligne 5 et 10, « ROI école »).
A5: 2. Les cellules sur fond JAUNE sont les hypothèses clés : celles qui changent le plus le résultat.
A6: 3. Les cellules en NOIR sont des formules : ne les écrasez pas. Les cellules en VERT reprennent une valeur d'un autre onglet.
A7: 4. Tous les montants sont en FCFA, hors taxes. Les années suivent l'année scolaire (An 1 = octobre 2026 à septembre 2027).
A9: Les onglets
A10: Hypothèses — clients, prix, charges, économie unitaire.
A11: Projection 3 ans — chiffre d'affaires, charges, résultat, revenu annuel récurrent.
A12: Trésorerie An 1 — mois par mois : quand l'argent rentre, quand il sort, et le besoin de financement de départ.
A13: Économie unitaire — ce que rapporte et coûte une école cliente (marge, coût d'acquisition, LTV).
A14: ROI école — le calcul à faire devant un fondateur pendant le rendez-vous commercial.
... A18: Un modèle n'est pas une promesse : il sert à décider et à repérer les leviers (nombre d'écoles, prix, commissions).

Sheet Hypothèses
A1: Hypothèses (modifiez les cellules en bleu)
A3: Hypothèse | B3: An 1 | C3: An 2 | D3: An 3 | E3: Unité | F3: Source / commentaire
A4: Clients
A5: Écoles clientes en fin d'année | B5: 40 | C5: 180 | D5: 500 | E5: écoles | F5: Objectifs du business plan (§11). An 1 : Côte d'Ivoire ; An 2 : + Sénégal ; An 3 : + 1 pays.
A6: Écoles actives en moyenne sur l'année | B6: ='Trésorerie An 1'!N5 -> 23.916667 | C6: 110 | D6: 340 | E6: écoles | F6: An 1 : moyenne mensuelle de l'onglet « Trésorerie An 1 ». An 2-3 : signatures concentrées à la rentrée et avant la 2e tranche (≈ moyenne début/fin d'année).
A7: Élèves moyens par école | B7: 350 | C7: 350 | D7: 350 | E7: élèves | F7: Hypothèse : école privée urbaine de taille moyenne. À valider lors des 30 premiers entretiens.
A8: Prix et revenus
A9: Prix Essentiel | B9: 500 | C9: 500 | D9: 500 | E9: FCFA/élève/an | F9: Offre ScolaPay (business plan §6). Repère marché : Novacole 200 à 500 FCFA/élève/an (novacole.com).
A10: Prix Recouvrement+ | B10: 1000 | C10: 1000 | D10: 1000 | E10: FCFA/élève/an | F10: Offre premium : paiement en ligne, revue mensuelle des impayés. Justifiée par le ROI (onglet « ROI école »).
A11: Part des écoles en Recouvrement+ | B11: 0.5 | C11: 0.5 | D11: 0.5 | E11: % | F11: Hypothèse : la moitié des écoles choisit l'offre premium.
A12: Services complémentaires par école active | B12: 37500 | C12: 57500 | D12: 87500 | E12: FCFA/an | F12: Cartes scolaires QR (≈ 550 FCFA de marge par carte), packs SMS, petite marge sur les paiements en ligne. Hypothèse croissante.
A13: Mise en place encaissée par nouvelle école | B13: 12500 | C13: 25000 | D13: 25000 | E13: FCFA | F13: 25 000 FCFA facturés ; offerte à environ la moitié des écoles en An 1 (lancement).
A14: Charges annuelles
A15: Salaire du fondateur | B15: ='Trésorerie An 1'!N10 -> 900000 | C15: 4800000 | D15: 9600000 | E15: FCFA/an | F15: An 1 : somme de la ligne 10 de l'onglet « Trésorerie An 1 » (0 pendant 6 mois, puis 150 000/mois). An 2 : 400 000/mois. An 3 : 800 000/mois.
A16: Commerciaux — salaires fixes | B16: 0 | C16: 3600000 | D16: 8640000 | E16: FCFA/an | F16: An 2 : 3 commerciaux × 100 000/mois. An 3 : 6 × 120 000/mois. An 1 : 100 % commission.
A17: Commissions commerciales (% du chiffre d'affaires) | B17: 0.2 | C17: 0.15 | D17: 0.1 | E17: % du CA | F17: 20 % de la 1re année des écoles signées ; la part baisse quand les réabonnements pèsent plus (kit commercial §10).
A18: Support et mise en place | B18: 0 | C18: 1800000 | D18: 6300000 | E18: FCFA/an | F18: An 2 : 1 chargé à 150 000/mois. An 3 : 3 à 175 000/mois.
A19: Développement et technique | B19: 0 | C19: 3600000 | D19: 12000000 | E19: FCFA/an | F19: An 1 : l'application existe déjà. An 2 : freelance 300 000/mois. An 3 : 2 développeurs.
A20: Responsables pays | B20: 0 | C20: 0 | D20: 9600000 | E20: FCFA/an | F20: An 3 : 2 responsables pays à 400 000/mois.
A21: Transport, téléphone, local | B21: 1200000 | C21: 3000000 | D21: 6000000 | E21: FCFA/an | F21: An 1 : ≈ 100 000/mois (transport 3 000/jour, crédit téléphone).
A22: Hébergement, SMS, outils | B22: 400000 | C22: 1500000 | D22: 4000000 | E22: FCFA/an | F22: Serveur, nom de domaine, SMS de relance, sauvegardes.
A23: Marketing (cartes, événements, contenus) | B23: 500000 | C23: 2500000 | D23: 8000000 | E23: FCFA/an | F23: Peu de publicité : la vente se fait sur le terrain et par recommandation.
A24: Juridique, comptabilité, création | B24: 500000 | C24: 1200000 | D24: 4000000 | E24: FCFA/an | F24: Création de l'entreprise, expert-comptable, contrats, dépôt de marque OAPI.
A25: Lancement de nouveaux pays | B25: 0 | C25: 2500000 | D25: 5000000 | E25: FCFA/an | F25: Missions, entité locale, premiers commerciaux.
A26: Économie unitaire et financement
A27: Coût de service par école | B27: 40000 | E27: FCFA/an | F27: Hébergement, SMS, environ 2 h de support par mois.
A28: Coût d'acquisition d'une école (CAC) | B28: 80000 | E28: FCFA | F28: Commission (≈ 20 % de la 1re année) + transport + démo.
A29: Attrition annuelle (écoles qui partent) | B29: 0.1 | E29: %/an | F29: Hypothèse prudente pour un outil qui contient toutes les données financières de l'école.
A30: Capital de départ | B30: 1000000 | E30: FCFA | F30: Épargne personnelle ou famille. Voir le besoin calculé dans « Trésorerie An 1 ».
A31: Durée de vie retenue au maximum | B31: 5 | E31: années | F31: Plafond prudent pour le calcul de la LTV, même si l'attrition laisse espérer plus longtemps.

Sheet Projection 3 ans
A1: Projection sur 3 ans (FCFA)
B3: An 1 | C3: An 2 | D3: An 3 | E3: Commentaire
A4: Clients
A5: Écoles en début d'année | B5: =0 -> 0 | C5: =B6 -> 40 | D5: =C6 -> 180
A6: Écoles en fin d'année | B6: =Hypothèses!B5 -> 40 | C6: =Hypothèses!C5 -> 180 | D6: =Hypothèses!D5 -> 500
A7: Nouvelles écoles (nettes) | B7: =B6-B5 -> 40 | C7: =C6-C5 -> 140 | D7: =D6-D5 -> 320
A8: Écoles actives en moyenne | B8: =Hypothèses!B6 -> 23.916667 | C8: =Hypothèses!C6 -> 110 | D8: =Hypothèses!D6 -> 340
A9: Élèves gérés en fin d'année | B9: =B6*Hypothèses!B7 -> 14000 | C9: =C6*Hypothèses!C7 -> 63000 | D9: =D6*Hypothèses!D7 -> 175000
A10: Revenu par école
A11: Prix moyen par élève | B11: =Hypothèses!B9*(1-Hypothèses!B11)+Hypothèses!B10*Hypothèses!B11 -> 750 | C11: =Hypothèses!C9*(1-Hypothèses!C11)+Hypothèses!C10*Hypothèses!C11 -> 750 | D11: =Hypothèses!D9*(1-Hypothèses!D11)+Hypothèses!D10*Hypothèses!D11 -> 750 | E11: Mix Essentiel / Recouvrement+
A12: Abonnement moyen par école | B12: =Hypothèses!B7*B11 -> 262500 | C12: =Hypothèses!C7*C11 -> 262500 | D12: =Hypothèses!D7*D11 -> 262500
A13: Revenu moyen par école (ARPA) | B13: =B12+Hypothèses!B12 -> 300000 | C13: =C12+Hypothèses!C12 -> 320000 | D13: =D12+Hypothèses!D12 -> 350000 | E13: Abonnement + services complémentaires
A14: Chiffre d'affaires
A15: Abonnements | B15: =B8*B12 -> 6278125 | C15: =C8*C12 -> 28875000 | D15: =D8*D12 -> 89250000
A16: Services complémentaires | B16: =B8*Hypothèses!B12 -> 896875 | C16: =C8*Hypothèses!C12 -> 6325000 | D16: =D8*Hypothèses!D12 -> 29750000
A17: Mises en place | B17: =B7*Hypothèses!B13 -> 500000 | C17: =C7*Hypothèses!C13 -> 3500000 | D17: =D7*Hypothèses!D13 -> 8000000
A18: Chiffre d'affaires total | B18: =SUM(B15:B17) -> 7675000 | C18: =SUM(C15:C17) -> 38700000 | D18: =SUM(D15:D17) -> 127000000
A19: Charges
A20: Salaire du fondateur | B20: =Hypothèses!B15 -> 900000 | C20: =Hypothèses!C15 -> 4800000 | D20: =Hypothèses!D15 -> 9600000
A21: Commerciaux — fixes | B21: =Hypothèses!B16 -> 0 | C21: =Hypothèses!C16 -> 3600000 | D21: =Hypothèses!D16 -> 8640000
A22: Commissions commerciales | B22: =Hypothèses!B17*B18 -> 1535000 | C22: =Hypothèses!C17*C18 -> 5805000 | D22: =Hypothèses!D17*D18 -> 12700000
A23: Support et mise en place | B23: =Hypothèses!B18 -> 0 | C23: =Hypothèses!C18 -> 1800000 | D23: =Hypothèses!D18 -> 6300000
A24: Développement et technique | B24: =Hypothèses!B19 -> 0 | C24: =Hypothèses!C19 -> 3600000 | D24: =Hypothèses!D19 -> 12000000
A25: Responsables pays | B25: =Hypothèses!B20 -> 0 | C25: =Hypothèses!C20 -> 0 | D25: =Hypothèses!D20 -> 9600000
A26: Transport, téléphone, local | B26: =Hypothèses!B21 -> 1200000 | C26: =Hypothèses!C21 -> 3000000 | D26: =Hypothèses!D21 -> 6000000
A27: Hébergement, SMS, outils | B27: =Hypothèses!B22 -> 400000 | C27: =Hypothèses!C22 -> 1500000 | D27: =Hypothèses!D22 -> 4000000
A28: Marketing | B28: =Hypothèses!B23 -> 500000 | C28: =Hypothèses!C23 -> 2500000 | D28: =Hypothèses!D23 -> 8000000
A29: Juridique, comptabilité | B29: =Hypothèses!B24 -> 500000 | C29: =Hypothèses!C24 -> 1200000 | D29: =Hypothèses!D24 -> 4000000
A30: Lancement de nouveaux pays | B30: =Hypothèses!B25 -> 0 | C30: =Hypothèses!C25 -> 2500000 | D30: =Hypothèses!D25 -> 5000000
A31: Total des charges | B31: =SUM(B20:B30) -> 5035000 | C31: =SUM(C20:C30) -> 30305000 | D31: =SUM(D20:D30) -> 85840000
A32: Résultat
A33: Résultat avant impôt | B33: =B18-B31 -> 2640000 | C33: =C18-C31 -> 8395000 | D33: =D18-D31 -> 41160000
A34: Marge (résultat / CA) | B34: =IF(B18=0,0,B33/B18) -> 0.34397394 | C34: =IF(C18=0,0,C33/C18) -> 0.21692506 | D34: =IF(D18=0,0,D33/D18) -> 0.32409449
A35: Résultat cumulé | B35: =B33 -> 2640000 | C35: =B35+C33 -> 11035000 | D35: =C35+D33 -> 52195000
A36: Revenu annuel récurrent en fin d'année | B36: =B6*B13 -> 12000000 | C36: =C6*C13 -> 57600000 | D36: =D6*D13 -> 175000000 | E36: Écoles en fin d'année × ARPA : ce que l'entreprise encaissera l'année suivante si personne ne part

Sheet Trésorerie An 1
A1: Trésorerie de l'An 1, mois par mois (FCFA)
A2: Lignes 5 et 10 en bleu : à ajuster. Le reste est calculé.
B4: oct-26 | C4: nov-26 | D4: déc-26 | E4: janv-27 | F4: févr-27 | G4: mars-27 | H4: avr-27 | I4: mai-27 | J4: juin-27 | K4: juil-27 | L4: août-27 | M4: sept-27 | N4: Total / moy.
A5: Écoles payantes (fin de mois) | B5: 0 | C5: 2 | D5: 8 | E5: 15 | F5: 20 | G5: 25 | H5: 30 | I5: 34 | J5: 36 | K5: 38 | L5: 39 | M5: 40 | N5: =AVERAGE(B5:M5) -> 23.916667
A6: Nouvelles écoles du mois | B6: =B5 -> 0 | C6: =MAX(0,C5-B5) -> 2 | D6: =MAX(0,D5-C5) -> 6 | E6: =MAX(0,E5-D5) -> 7 | F6: =MAX(0,F5-E5) -> 5 | G6: =MAX(0,G5-F5) -> 5 | H6: =MAX(0,H5-G5) -> 5 | I6: =MAX(0,I5-H5) -> 4 | J6: =MAX(0,J5-I5) -> 2 | ... M6: =MAX(0,M5-L5) -> 1 | N6: =SUM(B6:M6) -> 40
A7: Abonnements et services | B7: =B5*'Projection 3 ans'!$B$13/12 -> 0 | C7: =C5*'Projection 3 ans'!$B$13/12 -> 50000 | D7: =D5*'Projection 3 ans'!$B$13/12 -> 200000 | E7: =E5*'Projection 3 ans'!$B$13/12 -> 375000 | F7: =F5*'Projection 3 ans'!$B$13/12 -> 500000 | G7: =G5*'Projection 3 ans'!$B$13/12 -> 625000 | H7: =H5*'Projection 3 ans'!$B$13/12 -> 750000 | I7: =I5*'Projection 3 ans'!$B$13/12 -> 850000 | ... M7: =M5*'Projection 3 ans'!$B$13/12 -> 1000000 | N7: =SUM(B7:M7) -> 7175000
A8: Mises en place | B8: =B6*Hypothèses!$B$13 -> 0 | C8: =C6*Hypothèses!$B$13 -> 25000 | D8: =D6*Hypothèses!$B$13 -> 75000 | E8: =E6*Hypothèses!$B$13 -> 87500 | F8: =F6*Hypothèses!$B$13 -> 62500 | G8: =G6*Hypothèses!$B$13 -> 62500 | H8: =H6*Hypothèses!$B$13 -> 62500 | I8: =I6*Hypothèses!$B$13 -> 50000 | ... M8: =M6*Hypothèses!$B$13 -> 12500 | N8: =SUM(B8:M8) -> 500000
A9: Encaissements | B9: =B7+B8 -> 0 | C9: =C7+C8 -> 75000 | D9: =D7+D8 -> 275000 | E9: =E7+E8 -> 462500 | F9: =F7+F8 -> 562500 | G9: =G7+G8 -> 687500 | H9: =H7+H8 -> 812500 | I9: =I7+I8 -> 900000 | ... M9: =M7+M8 -> 1012500 | N9: =SUM(B9:M9) -> 7675000
A10: Salaire du fondateur | B10: 0 | C10: 0 | D10: 0 | E10: 0 | F10: 0 | G10: 0 | H10: 150000 | I10: 150000 | J10: 150000 | K10: 150000 | L10: 150000 | M10: 150000 | N10: =SUM(B10:M10) -> 900000
A11: Autres charges fixes | B11: =(Hypothèses!$B$16+Hypothèses!$B$18+Hypothèses!$B$19+Hypothèses!$B$20+Hypothèses!$B$21+Hypothèses!$B$22+Hypothèses!$B$23+Hypothèses!$B$24+Hypothèses!$B$25)/12 -> 216666.67 | C11: =(Hypothèses!$B$16+Hypothèses!$B$18+Hypothèses!$B$19+Hypothèses!$B$20+Hypothèses!$B$21+Hypothèses!$B$22+Hypothèses!$B$23+Hypothèses!$B$24+Hypothèses!$B$25)/12 -> 216666.67 | D11: =(Hypothèses!$B$16+Hypothèses!$B$18+Hypothèses!$B$19+Hypothèses!$B$20+Hypothèses!$B$21+Hypothèses!$B$22+Hypothèses!$B$23+Hypothèses!$B$24+Hypothèses!$B$25)/12 -> 216666.67 | E11: =(Hypothèses!$B$16+Hypothèses!$B$18+Hypothèses!$B$19+Hypothèses!$B$20+Hypothèses!$B$21+Hypothèses!$B$22+Hypothèses!$B$23+Hypothèses!$B$24+Hypothèses!$B$25)/12 -> 216666.67 | F11: =(Hypothèses!$B$16+Hypothèses!$B$18+Hypothèses!$B$19+Hypothèses!$B$20+Hypothèses!$B$21+Hypothèses!$B$22+Hypothèses!$B$23+Hypothèses!$B$24+Hypothèses!$B$25)/12 -> 216666.67 | G11: =(Hypothèses!$B$16+Hypothèses!$B$18+Hypothèses!$B$19+Hypothèses!$B$20+Hypothèses!$B$21+Hypothèses!$B$22+Hypothèses!$B$23+Hypothèses!$B$24+Hypothèses!$B$25)/12 -> 216666.67 | H11: =(Hypothèses!$B$16+Hypothèses!$B$18+Hypothèses!$B$19+Hypothèses!$B$20+Hypothèses!$B$21+Hypothèses!$B$22+Hypothèses!$B$23+Hypothèses!$B$24+Hypothèses!$B$25)/12 -> 216666.67 | I11: =(Hypothèses!$B$16+Hypothèses!$B$18+Hypothèses!$B$19+Hypothèses!$B$20+Hypothèses!$B$21+Hypothèses!$B$22+Hypothèses!$B$23+Hypothèses!$B$24+Hypothèses!$B$25)/12 -> 216666.67 | ... M11: =(Hypothèses!$B$16+Hypothèses!$B$18+Hypothèses!$B$19+Hypothèses!$B$20+Hypothèses!$B$21+Hypothèses!$B$22+Hypothèses!$B$23+Hypothèses!$B$24+Hypothèses!$B$25)/12 -> 216666.67 | N11: =SUM(B11:M11) -> 2600000
A12: Commissions commerciales | B12: =Hypothèses!$B$17*B9 -> 0 | C12: =Hypothèses!$B$17*C9 -> 15000 | D12: =Hypothèses!$B$17*D9 -> 55000 | E12: =Hypothèses!$B$17*E9 -> 92500 | F12: =Hypothèses!$B$17*F9 -> 112500 | G12: =Hypothèses!$B$17*G9 -> 137500 | H12: =Hypothèses!$B$17*H9 -> 162500 | I12: =Hypothèses!$B$17*I9 -> 180000 | ... M12: =Hypothèses!$B$17*M9 -> 202500 | N12: =SUM(B12:M12) -> 1535000
A13: Décaissements | B13: =B10+B11+B12 -> 216666.67 | C13: =C10+C11+C12 -> 231666.67 | D13: =D10+D11+D12 -> 271666.67 | E13: =E10+E11+E12 -> 309166.67 | F13: =F10+F11+F12 -> 329166.67 | G13: =G10+G11+G12 -> 354166.67 | H13: =H10+H11+H12 -> 529166.67 | I13: =I10+I11+I12 -> 546666.67 | ... M13: =M10+M11+M12 -> 569166.67 | N13: =SUM(B13:M13) -> 5035000
A14: Flux net du mois | B14: =B9-B13 -> -216666.67 | C14: =C9-C13 -> -156666.67 | D14: =D9-D13 -> 3333.3333 | E14: =E9-E13 -> 153333.33 | F14: =F9-F13 -> 233333.33 | G14: =G9-G13 -> 333333.33 | H14: =H9-H13 -> 283333.33 | I14: =I9-I13 -> 353333.33 | ... M14: =M9-M13 -> 443333.33 | N14: =SUM(B14:M14) -> 2640000
A15: Cumul des flux (sans capital) | B15: =B14 -> -216666.67 | C15: =B15+C14 -> -373333.33 | D15: =C15+D14 -> -370000 | E15: =D15+E14 -> -216666.67 | F15: =E15+F14 -> 16666.667 | G15: =F15+G14 -> 350000 | H15: =G15+H14 -> 633333.33 | I15: =H15+I14 -> 986666.67 | J15: =I15+J14 -> 1360000 | ... M15: =L15+M14 -> 2640000
A16: Trésorerie (avec capital de départ) | B16: =Hypothèses!$B$30+B15 -> 783333.33 | C16: =Hypothèses!$B$30+C15 -> 626666.67 | D16: =Hypothèses!$B$30+D15 -> 630000 | E16: =Hypothèses!$B$30+E15 -> 783333.33 | F16: =Hypothèses!$B$30+F15 -> 1016666.7 | G16: =Hypothèses!$B$30+G15 -> 1350000 | H16: =Hypothèses!$B$30+H15 -> 1633333.3 | I16: =Hypothèses!$B$30+I15 -> 1986666.7 | ... M16: =Hypothèses!$B$30+M15 -> 3640000
A18: Écoles actives en moyenne (An 1) | B18: =N5 -> 23.916667
A19: Besoin de financement (point bas de trésorerie) | B19: =MAX(0,-MIN(B15:M15)) -> 373333.33
A20: Trésorerie la plus basse avec le capital de départ | B20: =MIN(B16:M16) -> 626666.67
A21: Le capital de départ suffit-il ? | B21: =IF(B20>=0,"Oui","Non : augmentez le capital ou réduisez les charges") -> Oui
A23: Prudence : les revenus sont lissés sur 12 mois. En réalité, les écoles paient leur abonnement en 3 tranches (souvent à l'avance), ce qui améliore la trésorerie.

Sheet Économie unitaire
A1: Économie unitaire : ce que vaut une école cliente
B3: An 1 | C3: An 2 | D3: An 3 | E3: Commentaire
A4: Revenu moyen par école (ARPA, FCFA/an) | B4: ='Projection 3 ans'!B13 -> 300000 | C4: ='Projection 3 ans'!C13 -> 320000 | D4: ='Projection 3 ans'!D13 -> 350000
A5: Coût de service (FCFA/an) | B5: =Hypothèses!$B$27 -> 40000 | C5: =Hypothèses!$B$27 -> 40000 | D5: =Hypothèses!$B$27 -> 40000
A6: Marge brute par école (FCFA/an) | B6: =B4-B5 -> 260000 | C6: =C4-C5 -> 280000 | D6: =D4-D5 -> 310000
A7: Taux de marge brute | B7: =IF(B4=0,0,B6/B4) -> 0.86666667 | C7: =IF(C4=0,0,C6/C4) -> 0.875 | D7: =IF(D4=0,0,D6/D4) -> 0.88571429
A8: Coût d'acquisition (CAC, FCFA) | B8: =Hypothèses!$B$28 -> 80000 | C8: =Hypothèses!$B$28 -> 80000 | D8: =Hypothèses!$B$28 -> 80000
A9: Délai de remboursement du CAC (mois) | B9: =IF(B6=0,0,B8/(B6/12)) -> 3.6923077 | C9: =IF(C6=0,0,C8/(C6/12)) -> 3.4285714 | D9: =IF(D6=0,0,D8/(D6/12)) -> 3.0967742 | E9: Moins de 12 mois = excellent
A10: Durée de vie retenue d'une école (années) | B10: =IF(Hypothèses!$B$29=0,Hypothèses!$B$31,MIN(1/Hypothèses!$B$29,Hypothèses!$B$31)) -> 5 | C10: =IF(Hypothèses!$B$29=0,Hypothèses!$B$31,MIN(1/Hypothèses!$B$29,Hypothèses!$B$31)) -> 5 | D10: =IF(Hypothèses!$B$29=0,Hypothèses!$B$31,MIN(1/Hypothèses!$B$29,Hypothèses!$B$31)) -> 5 | E10: 1 / attrition, plafonnée (onglet Hypothèses)
A11: Valeur d'une école sur sa durée de vie (LTV, FCFA) | B11: =B6*B10 -> 1300000 | C11: =C6*C10 -> 1400000 | D11: =D6*D10 -> 1550000
A12: Ratio LTV / CAC | B12: =IF(B8=0,0,B11/B8) -> 16.25 | C12: =IF(C8=0,0,C11/C8) -> 17.5 | D12: =IF(D8=0,0,D11/D8) -> 19.375 | E12: Au-dessus de 3x : le modèle est sain

Sheet ROI école
A1: ROI pour l'école : à remplir devant le fondateur
A2: Remplacez les cellules bleues par les chiffres de l'école visitée.
B3: Valeur | C3: Commentaire
A4: Nombre d'élèves | B4: 400 | C4: Question 1 de l'entretien de découverte
A5: Scolarité annuelle moyenne (FCFA) | B5: 150000 | C5: Question 2
A6: Gain de recouvrement visé (points) | B6: 0.05 | C6: Prudent : 5 points. Beaucoup d'écoles partent de 70 % ou moins
A7: Prix ScolaPay (FCFA par élève et par an) | B7: 1000 | C7: 1 000 = Recouvrement+, 500 = Essentiel
A9: Total attendu dans l'année (FCFA) | B9: =B4*B5 -> 60000000
A10: Argent récupéré en plus (FCFA) | B10: =B9*B6 -> 3000000
A11: Coût de ScolaPay (FCFA) | B11: =B4*B7 -> 400000
A12: Gain net pour l'école (FCFA) | B12: =B10-B11 -> 2600000
A13: Retour sur investissement | B13: =IF(B11=0,0,B10/B11) -> 7.5 | C13: Francs récupérés pour 1 franc payé
A15: Sans compter : le temps gagné par la secrétaire, la fraude évitée à la caisse et les litiges en moins.
